Metadata-Version: 2.1
Name: ipywidgets-jsonschema
Version: 1.1.0
Summary: Widget Generator for JSON schema
Maintainer-email: Dominic Kempf <ssc@iwr.uni-heidelberg.de>
License: LICENSE.md
Classifier: License :: OSI Approved :: MIT License
Classifier: Operating System :: OS Independent
Classifier: Programming Language :: Python :: 3
License-File: LICENSE.md
Requires-Dist: IPython
Requires-Dist: ipywidgets
Requires-Dist: jsonschema<5
Requires-Dist: packaging
Requires-Dist: traitlets
